lambert/__init__.py
lambert-1.0.0.dist-info/METADATA
lambert-1.0.0.dist-info/WHEEL
lambert-1.0.0.dist-info/top_level.txt
lambert-1.0.0.dist-info/RECORD
