Metadata-Version: 2.1
Name: lambert
Version: 1.0.0
Summary: Convert location units from WS84 to Lambert (I,II,III) and reverse
Home-page: https://github.com/willena/lambert-python
Author: Willena
Author-email: contact@guillaumevillena.fr
License: MIT
Platform: UNKNOWN
Classifier: License :: OSI Approved :: MIT License
Classifier: Programming Language :: Python :: 3
Classifier: Programming Language :: Python :: 3.7
